django_sam/__init__.py
django_sam/middleware.py
tests/__init__.py
tests/test_middleware.py
django_sam-0.0.2.dist-info/LICENSE
django_sam-0.0.2.dist-info/METADATA
django_sam-0.0.2.dist-info/WHEEL
django_sam-0.0.2.dist-info/top_level.txt
django_sam-0.0.2.dist-info/RECORD
